setup.py
django_nginx_uwsgi.egg-info/PKG-INFO
django_nginx_uwsgi.egg-info/SOURCES.txt
django_nginx_uwsgi.egg-info/dependency_links.txt
django_nginx_uwsgi.egg-info/top_level.txt
dnuconfig/__init__.py
dnuconfig/dnuconfig.py
dnuconfig/dnuconfig.pyc
dnuconfig/nginx.conf
dnuconfig/settings.py
dnuconfig/settings.pyc
dnuconfig/test.py
dnuconfig/uwsgi.ini