Metadata-Version: 1.1
Name: django-nginx-uwsgi
Version: 0.0.4
Summary: Small module helps create nginx and uwsgi config files for deploy Django projects
Home-page: http://www.haikson.com/
Author: Kamo Petrosyan
Author-email: kamo@haikson.com
License: GPL3
Platform: UNKNOWN
Classifier: Development Status :: 5 - Production/Stable
Classifier: Intended Audience :: Developers
Classifier: Operating System :: OS Independent
Classifier: Programming Language :: Python
Classifier: Programming Language :: Python :: 2
Classifier: Programming Language :: Python :: 2.7
Classifier: Topic :: Software Development
Classifier: Topic :: Software Development :: Libraries :: Python Modules
